setup.py
httplibfix/__init__.py
httplibfix/patch.py
httplibfix.egg-info/PKG-INFO
httplibfix.egg-info/SOURCES.txt
httplibfix.egg-info/dependency_links.txt
httplibfix.egg-info/entry_points.txt
httplibfix.egg-info/not-zip-safe
httplibfix.egg-info/top_level.txt