Metadata-Version: 1.0
Name: httplibfix
Version: 1.0
Summary: A fix to httplib in python2.4 to back port a patch from trunk to fix issues with rss reads.
Home-page: http://pypi.python.org/pypi/httplibfix
Author: Matt Hamilton
Author-email: matth@netsight.co.uk
License: GPL
Keywords: python http httplib rss patch
Platform: UNKNOWN
